vagrant_creator/__init__.py
vagrant_creator/vagrant_creator.py
vagrant_creator_package_ChandulaJ/__init__.py
vagrant_creator_package_ChandulaJ/vagrant_creator.py
vagrant_creator-0.0.6.dist-info/METADATA
vagrant_creator-0.0.6.dist-info/WHEEL
vagrant_creator-0.0.6.dist-info/entry_points.txt
vagrant_creator-0.0.6.dist-info/top_level.txt
vagrant_creator-0.0.6.dist-info/RECORD
